more.itsdangerous-0.0.2-py2.7-nspkg.pth
more/itsdangerous/__init__.py
more/itsdangerous/identity_policy.py
more/itsdangerous/.gitignore
more/itsdangerous/tests/conftest.py
more/itsdangerous/tests/test_identity_policy.py
more.itsdangerous-0.0.2.dist-info/namespace_packages.txt
more.itsdangerous-0.0.2.dist-info/top_level.txt
more.itsdangerous-0.0.2.dist-info/METADATA
more.itsdangerous-0.0.2.dist-info/DESCRIPTION.rst
more.itsdangerous-0.0.2.dist-info/metadata.json
more.itsdangerous-0.0.2.dist-info/WHEEL
more.itsdangerous-0.0.2.dist-info/RECORD
