Metadata-Version: 2.0
Name: more.itsdangerous
Version: 0.0.2
Summary: An identity policy for morepath using itsdangerous.
Home-page: http://github.com/morepath/more.itsdangerous
Author: Seantis GmbH
Author-email: info@seantis.ch
License: BSD
Platform: any
Classifier: Intended Audience :: Developers
Classifier: Programming Language :: Python
Classifier: Programming Language :: Python :: 3
Classifier: Topic :: Software Development :: Libraries :: Python Modules
Classifier: License :: OSI Approved :: BSD License
Requires-Dist: itsdangerous
Requires-Dist: morepath
Provides-Extra: test
Requires-Dist: coverage; extra == 'test'
Requires-Dist: pytest; extra == 'test'
